{"items":[{"label":"574385215457a33d0c906f5c","uri":"https://openei.org/apps/USURDB/rate/view/574385215457a33d0c906f5c","revisions":[1464021185,1464021698,1500907694],"approved":true,"utility":"Baltimore Gas & Electric Co","eiaid":1167,"name":"Residential Optional Time of Use (Schedule RL)","startdate":1456794000,"enddate":1498780800,"supersedes":"555b99f15457a3082a42447c","sector":"Residential","description":"http://www.bge.com/myaccount/billsrates/ratestariffs/electricservice/Electric%20Services%20Rates%20and%20Tariffs/Rdr_1.pdf","source":"http://www.bge.com/myaccount/billsrates/ratestariffs/electricservice/Electric%20Services%20Rates%20and%20Tariffs/P3_SCH_RL.pdf","basicinformationcomments":"there is also a competitive billing charge of .62\r\nFRA showed on attachment","flatdemandunit":"kW","demandrateunit":"kW","energyratestructure":[[{"unit":"kWh","rate":0.15109,"adj":0.01147}],[{"unit":"kWh","rate":0.11004,"adj":0.01147}],[{"unit":"kWh","rate":0.10607,"adj":0.01147}],[{"unit":"kWh","rate":0.15057,"adj":0.01147}],[{"unit":"kWh","rate":0.13004,"adj":0.01147}],[{"unit":"kWh","rate":0.11088,"adj":0.01147}]],"energyweekdayschedule":[[5,5,5,5,5,5,5,3,3,3,3,4,4,4,4,4,4,3,3,3,3,5,5,5],[5,5,5,5,5,5,5,3,3,3,3,4,4,4,4,4,4,3,3,3,3,5,5,5],[5,5,5,5,5,5,5,3,3,3,3,4,4,4,4,4,4,3,3,3,3,5,5,5],[5,5,5,5,5,5,5,3,3,3,3,4,4,4,4,4,4,3,3,3,3,5,5,5],[5,5,5,5,5,5,5,3,3,3,3,4,4,4,4,4,4,3,3,3,3,5,5,5],[2,2,2,2,2,2,2,1,1,1,0,0,0,0,0,0,0,0,0,0,1,1,1,2],[2,2,2,2,2,2,2,1,1,1,0,0,0,0,0,0,0,0,0,0,1,1,1,2],[2,2,2,2,2,2,2,1,1,1,0,0,0,0,0,0,0,0,0,0,1,1,1,2],[2,2,2,2,2,2,2,1,1,1,0,0,0,0,0,0,0,0,0,0,1,1,1,2],[5,5,5,5,5,5,5,3,3,3,3,4,4,4,4,4,4,3,3,3,3,5,5,5],[5,5,5,5,5,5,5,3,3,3,3,4,4,4,4,4,4,3,3,3,3,5,5,5],[5,5,5,5,5,5,5,3,3,3,3,4,4,4,4,4,4,3,3,3,3,5,5,5]],"energyweekendschedule":[[5,5,5,5,5,5,5,5,5,5,5,5,5,5,5,5,5,5,5,5,5,5,5,5],[5,5,5,5,5,5,5,5,5,5,5,5,5,5,5,5,5,5,5,5,5,5,5,5],[5,5,5,5,5,5,5,5,5,5,5,5,5,5,5,5,5,5,5,5,5,5,5,5],[5,5,5,5,5,5,5,5,5,5,5,5,5,5,5,5,5,5,5,5,5,5,5,5],[5,5,5,5,5,5,5,5,5,5,5,5,5,5,5,5,5,5,5,5,5,5,5,5],[2,2,2,2,2,2,2,2,2,2,2,2,2,2,2,2,2,2,2,2,2,2,2,2],[2,2,2,2,2,2,2,2,2,2,2,2,2,2,2,2,2,2,2,2,2,2,2,2],[2,2,2,2,2,2,2,2,2,2,2,2,2,2,2,2,2,2,2,2,2,2,2,2],[2,2,2,2,2,2,2,2,2,2,2,2,2,2,2,2,2,2,2,2,2,2,2,2],[5,5,5,5,5,5,5,5,5,5,5,5,5,5,5,5,5,5,5,5,5,5,5,5],[5,5,5,5,5,5,5,5,5,5,5,5,5,5,5,5,5,5,5,5,5,5,5,5],[5,5,5,5,5,5,5,5,5,5,5,5,5,5,5,5,5,5,5,5,5,5,5,5]],"energycomments":"Rate = Generation + Transmission + Delivery.  Adjustments = Electric Efficiency charge + Energy Cost adjustment + Administrative Cost adjustment + Demand Response rider + Nuclear Decommissioning and Standard Offer Service Return credits + Financing credit + Rate Stabilization Plan charge + Peak Time rebate + Demand Resource charge + Electric Reliability Initiative surcharge","fixedmonthlycharge":12}]}