{"items":[{"label":"539fca73ec4f024d2f53fbe8","uri":"https://openei.org/apps/USURDB/rate/view/539fca73ec4f024d2f53fbe8","approved":true,"demandrateunit":"kW","description":"Residential purposes in towns, villages, farming areas, permanent rental\nunits, and farming related non-residential uses subject to the established rules and regulations of the Association. To small rural civic services where the transformer capacity does not exceed 10 kVa. This rate not for resale. This schedule is for alternating current supplied at approximately 120 or\n240 volts, single-phase through one kilowatt hour meter at a single point of delivery. Service is not to be used to supply a second dwelling.\nMINIMUM MONTHLY CHARGE:$16.00 plus any increase required under the Line Extension Policy.\nRECONNECTION FEE: When a reconnect is made for the same consumer at the same or\nanother location after voluntary disconnection, a $10.00 fee shall be charged.","startdate":962431200,"eiaid":12866,"energyratestructure":[[{"max":700,"rate":0.0615,"unit":"kWh"},{"max":1500,"rate":0.056,"unit":"kWh"},{"rate":0.037,"unit":"kWh"}]],"energyweekdayschedule":[[0,0,0,0,0,0,0,0,0,0,0,0,0,0,0,0,0,0,0,0,0,0,0,0],[0,0,0,0,0,0,0,0,0,0,0,0,0,0,0,0,0,0,0,0,0,0,0,0],[0,0,0,0,0,0,0,0,0,0,0,0,0,0,0,0,0,0,0,0,0,0,0,0],[0,0,0,0,0,0,0,0,0,0,0,0,0,0,0,0,0,0,0,0,0,0,0,0],[0,0,0,0,0,0,0,0,0,0,0,0,0,0,0,0,0,0,0,0,0,0,0,0],[0,0,0,0,0,0,0,0,0,0,0,0,0,0,0,0,0,0,0,0,0,0,0,0],[0,0,0,0,0,0,0,0,0,0,0,0,0,0,0,0,0,0,0,0,0,0,0,0],[0,0,0,0,0,0,0,0,0,0,0,0,0,0,0,0,0,0,0,0,0,0,0,0],[0,0,0,0,0,0,0,0,0,0,0,0,0,0,0,0,0,0,0,0,0,0,0,0],[0,0,0,0,0,0,0,0,0,0,0,0,0,0,0,0,0,0,0,0,0,0,0,0],[0,0,0,0,0,0,0,0,0,0,0,0,0,0,0,0,0,0,0,0,0,0,0,0],[0,0,0,0,0,0,0,0,0,0,0,0,0,0,0,0,0,0,0,0,0,0,0,0]],"energyweekendschedule":[[0,0,0,0,0,0,0,0,0,0,0,0,0,0,0,0,0,0,0,0,0,0,0,0],[0,0,0,0,0,0,0,0,0,0,0,0,0,0,0,0,0,0,0,0,0,0,0,0],[0,0,0,0,0,0,0,0,0,0,0,0,0,0,0,0,0,0,0,0,0,0,0,0],[0,0,0,0,0,0,0,0,0,0,0,0,0,0,0,0,0,0,0,0,0,0,0,0],[0,0,0,0,0,0,0,0,0,0,0,0,0,0,0,0,0,0,0,0,0,0,0,0],[0,0,0,0,0,0,0,0,0,0,0,0,0,0,0,0,0,0,0,0,0,0,0,0],[0,0,0,0,0,0,0,0,0,0,0,0,0,0,0,0,0,0,0,0,0,0,0,0],[0,0,0,0,0,0,0,0,0,0,0,0,0,0,0,0,0,0,0,0,0,0,0,0],[0,0,0,0,0,0,0,0,0,0,0,0,0,0,0,0,0,0,0,0,0,0,0,0],[0,0,0,0,0,0,0,0,0,0,0,0,0,0,0,0,0,0,0,0,0,0,0,0],[0,0,0,0,0,0,0,0,0,0,0,0,0,0,0,0,0,0,0,0,0,0,0,0],[0,0,0,0,0,0,0,0,0,0,0,0,0,0,0,0,0,0,0,0,0,0,0,0]],"name":"Residential Service","revisions":[1339092434,1339092452,1354891449,1369075169,1369076492,1427405186],"sector":"Residential","source":"http://www.moonlakeelectric.com/rates.html","utility":"Moon Lake Electric Assn Inc","fixedmonthlycharge":6.5}]}