{"items":[{"label":"58b5bd3f5457a34e17fbf84d","uri":"https://openei.org/apps/USURDB/rate/view/58b5bd3f5457a34e17fbf84d","revisions":[1488280271,1488280406],"approved":true,"utility":"Northern States Power Co - Minnesota","eiaid":13781,"name":"Residential TOD Overhead Standard (A02)","startdate":1485907200,"supersedes":"575f198d5457a3292bba0c14","sector":"Residential","description":"Available to any residential customer for domestic purposes only in a single private residence and qualifying\r\nfarm customers.","source":"https://www.xcelenergy.com/staticfiles/xe/Regulatory/Regulatory%20PDFs/rates/MN/Me_Section_5.pdf","sourceparent":"https://www.xcelenergy.com/billing_and_payment/understanding_your_bill/understanding_your_residential_rates","phasewiring":"Single Phase","flatdemandunit":"kW","demandrateunit":"kW","energyratestructure":[[{"unit":"kWh","rate":0.03015,"adj":0.030541}],[{"unit":"kWh","rate":0.16454,"adj":0.030541}],[{"unit":"kWh","rate":0.03015,"adj":0.030541}],[{"unit":"kWh","rate":0.20077,"adj":0.030541}]],"energyweekdayschedule":[[0,0,0,0,0,0,0,0,0,1,1,1,1,1,1,1,1,1,1,1,1,0,0,0],[0,0,0,0,0,0,0,0,0,1,1,1,1,1,1,1,1,1,1,1,1,0,0,0],[0,0,0,0,0,0,0,0,0,1,1,1,1,1,1,1,1,1,1,1,1,0,0,0],[0,0,0,0,0,0,0,0,0,1,1,1,1,1,1,1,1,1,1,1,1,0,0,0],[0,0,0,0,0,0,0,0,0,1,1,1,1,1,1,1,1,1,1,1,1,0,0,0],[2,2,2,2,2,2,2,2,2,3,3,3,3,3,3,3,3,3,3,3,3,2,2,2],[2,2,2,2,2,2,2,2,2,3,3,3,3,3,3,3,3,3,3,3,3,2,2,2],[2,2,2,2,2,2,2,2,2,3,3,3,3,3,3,3,3,3,3,3,3,2,2,2],[2,2,2,2,2,2,2,2,2,3,3,3,3,3,3,3,3,3,3,3,3,2,2,2],[0,0,0,0,0,0,0,0,0,1,1,1,1,1,1,1,1,1,1,1,1,0,0,0],[0,0,0,0,0,0,0,0,0,1,1,1,1,1,1,1,1,1,1,1,1,0,0,0],[0,0,0,0,0,0,0,0,0,1,1,1,1,1,1,1,1,1,1,1,1,0,0,0]],"energyweekendschedule":[[0,0,0,0,0,0,0,0,0,0,0,0,0,0,0,0,0,0,0,0,0,0,0,0],[0,0,0,0,0,0,0,0,0,0,0,0,0,0,0,0,0,0,0,0,0,0,0,0],[0,0,0,0,0,0,0,0,0,0,0,0,0,0,0,0,0,0,0,0,0,0,0,0],[0,0,0,0,0,0,0,0,0,0,0,0,0,0,0,0,0,0,0,0,0,0,0,0],[0,0,0,0,0,0,0,0,0,0,0,0,0,0,0,0,0,0,0,0,0,0,0,0],[2,2,2,2,2,2,2,2,2,2,2,2,2,2,2,2,2,2,2,2,2,2,2,2],[2,2,2,2,2,2,2,2,2,2,2,2,2,2,2,2,2,2,2,2,2,2,2,2],[2,2,2,2,2,2,2,2,2,2,2,2,2,2,2,2,2,2,2,2,2,2,2,2],[2,2,2,2,2,2,2,2,2,2,2,2,2,2,2,2,2,2,2,2,2,2,2,2],[0,0,0,0,0,0,0,0,0,0,0,0,0,0,0,0,0,0,0,0,0,0,0,0],[0,0,0,0,0,0,0,0,0,0,0,0,0,0,0,0,0,0,0,0,0,0,0,0],[0,0,0,0,0,0,0,0,0,0,0,0,0,0,0,0,0,0,0,0,0,0,0,0]],"energycomments":"Adjustments = Fuel Cost charge + Transmission Cost Recovery rider + Conservation Improvement Program adjustment + Renewable Development Fund rider","fixedmonthlycharge":10}]}