{"items":[{"label":"539f7316ec4f024411ecf8e1","uri":"https://openei.org/apps/USURDB/rate/view/539f7316ec4f024411ecf8e1","revisions":[1329764934,1329765327,1340830917,1354881568,1376055993,1401807447,1408699325,1427405192,1434380606],"approved":true,"utility":"City of Bentonville, Arkansas (Utility Company)","eiaid":1586,"name":"Residential","startdate":1230771600,"sector":"Residential","description":"Net Metering\r\n\r\n*Available to any customer who has installed a net metering facility and signed an Interconnection Agreement with the City of Bentonville. Such facilities must be located on the Customer's premise and intended primarily to offset some of all of the Customer's energy usage at that location. The generating capacity of net metering facilities may not exceed twenty-five kilowatts (25kW).\r\n\r\n*Minimum Monthly Charge = $12.00","source":"http://www.bentonvillear.com/assets/electric_files/BEUD_-_Electric_Rate_Schedule.pdf","sourceparent":"http://www.bentonvillear.com/departments/electric-department","flatdemandunit":"kW","demandrateunit":"kW","energyratestructure":[[{"max":800,"unit":"kWh","rate":0.1,"sell":0.1},{"unit":"kWh","rate":0.076,"sell":0.076}],[{"max":800,"unit":"kWh","rate":0.1,"sell":0.1},{"unit":"kWh","rate":0.092,"sell":0.092}]],"energyweekdayschedule":[[0,0,0,0,0,0,0,0,0,0,0,0,0,0,0,0,0,0,0,0,0,0,0,0],[0,0,0,0,0,0,0,0,0,0,0,0,0,0,0,0,0,0,0,0,0,0,0,0],[0,0,0,0,0,0,0,0,0,0,0,0,0,0,0,0,0,0,0,0,0,0,0,0],[0,0,0,0,0,0,0,0,0,0,0,0,0,0,0,0,0,0,0,0,0,0,0,0],[1,1,1,1,1,1,1,1,1,1,1,1,1,1,1,1,1,1,1,1,1,1,1,1],[1,1,1,1,1,1,1,1,1,1,1,1,1,1,1,1,1,1,1,1,1,1,1,1],[1,1,1,1,1,1,1,1,1,1,1,1,1,1,1,1,1,1,1,1,1,1,1,1],[1,1,1,1,1,1,1,1,1,1,1,1,1,1,1,1,1,1,1,1,1,1,1,1],[1,1,1,1,1,1,1,1,1,1,1,1,1,1,1,1,1,1,1,1,1,1,1,1],[1,1,1,1,1,1,1,1,1,1,1,1,1,1,1,1,1,1,1,1,1,1,1,1],[0,0,0,0,0,0,0,0,0,0,0,0,0,0,0,0,0,0,0,0,0,0,0,0],[0,0,0,0,0,0,0,0,0,0,0,0,0,0,0,0,0,0,0,0,0,0,0,0]],"energyweekendschedule":[[0,0,0,0,0,0,0,0,0,0,0,0,0,0,0,0,0,0,0,0,0,0,0,0],[0,0,0,0,0,0,0,0,0,0,0,0,0,0,0,0,0,0,0,0,0,0,0,0],[0,0,0,0,0,0,0,0,0,0,0,0,0,0,0,0,0,0,0,0,0,0,0,0],[0,0,0,0,0,0,0,0,0,0,0,0,0,0,0,0,0,0,0,0,0,0,0,0],[1,1,1,1,1,1,1,1,1,1,1,1,1,1,1,1,1,1,1,1,1,1,1,1],[1,1,1,1,1,1,1,1,1,1,1,1,1,1,1,1,1,1,1,1,1,1,1,1],[1,1,1,1,1,1,1,1,1,1,1,1,1,1,1,1,1,1,1,1,1,1,1,1],[1,1,1,1,1,1,1,1,1,1,1,1,1,1,1,1,1,1,1,1,1,1,1,1],[1,1,1,1,1,1,1,1,1,1,1,1,1,1,1,1,1,1,1,1,1,1,1,1],[1,1,1,1,1,1,1,1,1,1,1,1,1,1,1,1,1,1,1,1,1,1,1,1],[0,0,0,0,0,0,0,0,0,0,0,0,0,0,0,0,0,0,0,0,0,0,0,0],[0,0,0,0,0,0,0,0,0,0,0,0,0,0,0,0,0,0,0,0,0,0,0,0]],"energycomments":"there is a minimum charge of 12 dollars which is charged by the utility.","fixedmonthlycharge":6}]}