{"items":[{"label":"539f6accec4f024411ec943d","uri":"https://openei.org/apps/USURDB/rate/view/539f6accec4f024411ec943d","approved":true,"demandrateunit":"kW","description":"Time of Use\n\nFor any customer presently taking service or eligible to take service under the Light Plant's Schedule A and having installed an off-peak Electric Thermal Storage (ETS) system with the following provisions: -energy consumed during the off-peak periods as defined below will be at this off-peak rate\n-loads served under this off-peak provision must be directly controlled by and acceptable to the Light Plant\n-loads served under this off-peak provision must make a positive contribution towards the Light Plant's system load factor.  This rate schedule is applicable to all electric service required by the customer exclusively for domestic purposes for individual (single-family) private residences and individually-metered apartment units. The electrical connection of any equipment and/or appliance(s) installed so as to use off-peak energy under this rate must be inspected and approved by the Light Plant. The electrical supply to the off-peak equipment and/or appliance(s) must be controlled by the Light Plant.\n\nThe Light Plant's Hydropower Adjustment Clause, M.D.T.E. #136, will apply to all KWH sold under this schedule.","eiaid":18546,"energyratestructure":[[{"rate":0.154,"unit":"kWh"}],[{"rate":0.0789,"unit":"kWh"}]],"energyweekdayschedule":[[1,1,1,1,1,1,1,1,0,0,0,0,0,0,0,0,0,0,0,0,0,1,1,1],[1,1,1,1,1,1,1,1,0,0,0,0,0,0,0,0,0,0,0,0,0,1,1,1],[1,1,1,1,1,1,1,1,0,0,0,0,0,0,0,0,0,0,0,0,0,1,1,1],[1,1,1,1,1,1,1,1,0,0,0,0,0,0,0,0,0,0,0,0,0,1,1,1],[1,1,1,1,1,1,1,1,0,0,0,0,0,0,0,0,0,0,0,0,0,1,1,1],[1,1,1,1,1,1,1,1,0,0,0,0,0,0,0,0,0,0,0,0,0,1,1,1],[1,1,1,1,1,1,1,1,0,0,0,0,0,0,0,0,0,0,0,0,0,1,1,1],[1,1,1,1,1,1,1,1,0,0,0,0,0,0,0,0,0,0,0,0,0,1,1,1],[1,1,1,1,1,1,1,1,0,0,0,0,0,0,0,0,0,0,0,0,0,1,1,1],[1,1,1,1,1,1,1,1,0,0,0,0,0,0,0,0,0,0,0,0,0,1,1,1],[1,1,1,1,1,1,1,1,0,0,0,0,0,0,0,0,0,0,0,0,0,1,1,1],[1,1,1,1,1,1,1,1,0,0,0,0,0,0,0,0,0,0,0,0,0,1,1,1]],"energyweekendschedule":[[1,1,1,1,1,1,1,1,1,1,1,1,1,1,1,1,1,1,1,1,1,1,1,1],[1,1,1,1,1,1,1,1,1,1,1,1,1,1,1,1,1,1,1,1,1,1,1,1],[1,1,1,1,1,1,1,1,1,1,1,1,1,1,1,1,1,1,1,1,1,1,1,1],[1,1,1,1,1,1,1,1,1,1,1,1,1,1,1,1,1,1,1,1,1,1,1,1],[1,1,1,1,1,1,1,1,1,1,1,1,1,1,1,1,1,1,1,1,1,1,1,1],[1,1,1,1,1,1,1,1,1,1,1,1,1,1,1,1,1,1,1,1,1,1,1,1],[1,1,1,1,1,1,1,1,1,1,1,1,1,1,1,1,1,1,1,1,1,1,1,1],[1,1,1,1,1,1,1,1,1,1,1,1,1,1,1,1,1,1,1,1,1,1,1,1],[1,1,1,1,1,1,1,1,1,1,1,1,1,1,1,1,1,1,1,1,1,1,1,1],[1,1,1,1,1,1,1,1,1,1,1,1,1,1,1,1,1,1,1,1,1,1,1,1],[1,1,1,1,1,1,1,1,1,1,1,1,1,1,1,1,1,1,1,1,1,1,1,1],[1,1,1,1,1,1,1,1,1,1,1,1,1,1,1,1,1,1,1,1,1,1,1,1]],"flatdemandmonths":[0,0,0,0,0,0,0,0,0,0,0,0],"flatdemandstructure":[[{"max":10,"rate":0},{"rate":2.5}]],"flatdemandunit":"kW","name":"Schedule A-2: Residential Time-of-Use","revisions":[1370291434,1370291831,1371763250,1373482522,1427405217],"sector":"Residential","source":"http://www.templetonlight.com/ElectricRatesPrices.html","utility":"Town of Templeton, Massachusetts (Utility Company)","fixedmonthlycharge":6}]}