{"items":[{"label":"539fc14aec4f024c27d8a557","uri":"https://openei.org/apps/USURDB/rate/view/539fc14aec4f024c27d8a557","approved":true,"demandrateunit":"kW","description":"Only single phase service supplied where no more than 26 kVa of installed or allocated name plate rated transformer capacity is required to serve what is ordinarily designated and recognized as individual Single Family Homes, Apartments, Mobile Homes, and other individual Single Family Dwelling Quarters, including incidental farm use.","startdate":1325397600,"eiaid":5653,"energyratestructure":[[{"max":500,"rate":0.103,"adj":0.0355,"unit":"kWh"},{"max":1000,"rate":0.098,"adj":0.0355,"unit":"kWh"},{"rate":0.093,"adj":0.0355,"unit":"kWh"}]],"energyweekdayschedule":[[0,0,0,0,0,0,0,0,0,0,0,0,0,0,0,0,0,0,0,0,0,0,0,0],[0,0,0,0,0,0,0,0,0,0,0,0,0,0,0,0,0,0,0,0,0,0,0,0],[0,0,0,0,0,0,0,0,0,0,0,0,0,0,0,0,0,0,0,0,0,0,0,0],[0,0,0,0,0,0,0,0,0,0,0,0,0,0,0,0,0,0,0,0,0,0,0,0],[0,0,0,0,0,0,0,0,0,0,0,0,0,0,0,0,0,0,0,0,0,0,0,0],[0,0,0,0,0,0,0,0,0,0,0,0,0,0,0,0,0,0,0,0,0,0,0,0],[0,0,0,0,0,0,0,0,0,0,0,0,0,0,0,0,0,0,0,0,0,0,0,0],[0,0,0,0,0,0,0,0,0,0,0,0,0,0,0,0,0,0,0,0,0,0,0,0],[0,0,0,0,0,0,0,0,0,0,0,0,0,0,0,0,0,0,0,0,0,0,0,0],[0,0,0,0,0,0,0,0,0,0,0,0,0,0,0,0,0,0,0,0,0,0,0,0],[0,0,0,0,0,0,0,0,0,0,0,0,0,0,0,0,0,0,0,0,0,0,0,0],[0,0,0,0,0,0,0,0,0,0,0,0,0,0,0,0,0,0,0,0,0,0,0,0]],"energyweekendschedule":[[0,0,0,0,0,0,0,0,0,0,0,0,0,0,0,0,0,0,0,0,0,0,0,0],[0,0,0,0,0,0,0,0,0,0,0,0,0,0,0,0,0,0,0,0,0,0,0,0],[0,0,0,0,0,0,0,0,0,0,0,0,0,0,0,0,0,0,0,0,0,0,0,0],[0,0,0,0,0,0,0,0,0,0,0,0,0,0,0,0,0,0,0,0,0,0,0,0],[0,0,0,0,0,0,0,0,0,0,0,0,0,0,0,0,0,0,0,0,0,0,0,0],[0,0,0,0,0,0,0,0,0,0,0,0,0,0,0,0,0,0,0,0,0,0,0,0],[0,0,0,0,0,0,0,0,0,0,0,0,0,0,0,0,0,0,0,0,0,0,0,0],[0,0,0,0,0,0,0,0,0,0,0,0,0,0,0,0,0,0,0,0,0,0,0,0],[0,0,0,0,0,0,0,0,0,0,0,0,0,0,0,0,0,0,0,0,0,0,0,0],[0,0,0,0,0,0,0,0,0,0,0,0,0,0,0,0,0,0,0,0,0,0,0,0],[0,0,0,0,0,0,0,0,0,0,0,0,0,0,0,0,0,0,0,0,0,0,0,0],[0,0,0,0,0,0,0,0,0,0,0,0,0,0,0,0,0,0,0,0,0,0,0,0]],"flatdemandmonths":[0,0,0,0,0,0,0,0,0,0,0,0],"flatdemandstructure":[[{"max":20,"rate":0},{"rate":2}]],"flatdemandunit":"kW","name":"Residential","revisions":[1339789999,1339790197,1339790316,1354940833,1365007782,1371051437,1371051472,1378758652,1400703269,1401910247,1427405185],"sector":"Residential","source":"ISU Documentation","utility":"Village of Edgerton, Ohio (Utility Company)","fixedmonthlycharge":4}]}